rebay/__init__.py
rebay/browser.py
rebay/engine.py
rebay/geckodriver_installer.py
rebay/listing_globber.py
rebay/mappings.json
rebay/models.py
rebay/parsers.py
rebay/scan_listing.py
rebay/utilities.py
rebay-0.10.3.dist-info/METADATA
rebay-0.10.3.dist-info/WHEEL
rebay-0.10.3.dist-info/entry_points.txt
rebay-0.10.3.dist-info/RECORD
