Metadata-Version: 2.4
Name: rebay
Version: 0.10.3
Summary: Scrape an ebay shop's inventory into a Reverb compatible format.
Project-URL: Homepage, https://github.com/matt-manes/rebay
Project-URL: Documentation, https://github.com/matt-manes/rebay/tree/main/docs
Project-URL: Source code, https://github.com/matt-manes/rebay/tree/main/src/rebay
Author-email: Matt Manes <mattmanes@pm.me>
Classifier: Operating System :: OS Independent
Classifier: Programming Language :: Python :: 3
Requires-Python: <3.12,>=3.10
Requires-Dist: beautifulsoup4>=4.12.3
Requires-Dist: dacite>=1.8.1
Requires-Dist: gruel>=4.6.0
Requires-Dist: loggi>=0.5.0
Requires-Dist: pathier>=1.5.4
Requires-Dist: printbuddies>=2.1.3
Requires-Dist: quickpool>=2.2.0
Requires-Dist: requests>=2.32.3
Requires-Dist: rich>=13.7.1
Requires-Dist: seleniumuser>=1.1.4
Requires-Dist: typing-extensions>=4.12.2
